dspy/__init__.py
dspy/__metadata__.py
dspy/adapters/__init__.py
dspy/adapters/baml_adapter.py
dspy/adapters/base.py
dspy/adapters/chat_adapter.py
dspy/adapters/json_adapter.py
dspy/adapters/two_step_adapter.py
dspy/adapters/utils.py
dspy/adapters/xml_adapter.py
dspy/adapters/types/__init__.py
dspy/adapters/types/audio.py
dspy/adapters/types/base_type.py
dspy/adapters/types/code.py
dspy/adapters/types/history.py
dspy/adapters/types/image.py
dspy/adapters/types/tool.py
dspy/clients/__init__.py
dspy/clients/base_lm.py
dspy/clients/cache.py
dspy/clients/databricks.py
dspy/clients/embedding.py
dspy/clients/lm.py
dspy/clients/lm_local.py
dspy/clients/lm_local_arbor.py
dspy/clients/openai.py
dspy/clients/provider.py
dspy/clients/utils_finetune.py
dspy/datasets/__init__.py
dspy/datasets/colors.py
dspy/datasets/dataloader.py
dspy/datasets/dataset.py
dspy/datasets/gsm8k.py
dspy/datasets/hotpotqa.py
dspy/datasets/math.py
dspy/datasets/alfworld/__init__.py
dspy/datasets/alfworld/alfworld.py
dspy/dsp/__init__.py
dspy/dsp/colbertv2.py
dspy/dsp/utils/__init__.py
dspy/dsp/utils/dpr.py
dspy/dsp/utils/settings.py
dspy/dsp/utils/utils.py
dspy/evaluate/__init__.py
dspy/evaluate/auto_evaluation.py
dspy/evaluate/evaluate.py
dspy/evaluate/metrics.py
dspy/predict/__init__.py
dspy/predict/aggregation.py
dspy/predict/best_of_n.py
dspy/predict/chain_of_thought.py
dspy/predict/code_act.py
dspy/predict/knn.py
dspy/predict/multi_chain_comparison.py
dspy/predict/parallel.py
dspy/predict/parameter.py
dspy/predict/predict.py
dspy/predict/program_of_thought.py
dspy/predict/react.py
dspy/predict/refine.py
dspy/predict/retry.py
dspy/predict/avatar/__init__.py
dspy/predict/avatar/avatar.py
dspy/predict/avatar/models.py
dspy/predict/avatar/signatures.py
dspy/primitives/__init__.py
dspy/primitives/base_module.py
dspy/primitives/example.py
dspy/primitives/module.py
dspy/primitives/prediction.py
dspy/primitives/python_interpreter.py
dspy/primitives/runner.js
dspy/propose/__init__.py
unpage_dspy-3.0.0.dist-info/licenses/LICENSE
unpage_dspy-3.0.0.dist-info/METADATA
unpage_dspy-3.0.0.dist-info/WHEEL
unpage_dspy-3.0.0.dist-info/top_level.txt
unpage_dspy-3.0.0.dist-info/RECORD
