Metadata-Version: 2.4
Name: unpage-dspy
Version: 3.0.0
Summary: DSPy
Author-email: Omar Khattab <okhattab@stanford.edu>
License-Expression: MIT
Project-URL: homepage, https://github.com/stanfordnlp/dspy
Classifier: Development Status :: 3 - Alpha
Classifier: Intended Audience :: Science/Research
Classifier: Operating System :: POSIX :: Linux
Classifier: Programming Language :: Python :: 3
Requires-Python: <3.14,>=3.10
License-File: LICENSE
Requires-Dist: backoff>=2.2
Requires-Dist: joblib~=1.3
Requires-Dist: openai>=0.28.1
Requires-Dist: regex>=2023.10.3
Requires-Dist: ujson>=5.8.0
Requires-Dist: tqdm>=4.66.1
Requires-Dist: requests>=2.31.0
Requires-Dist: optuna>=3.4.0
Requires-Dist: pydantic>=2.0
Requires-Dist: magicattr>=0.1.6
Requires-Dist: litellm>=1.64.0
Requires-Dist: diskcache>=5.6.0
Requires-Dist: json-repair>=0.30.0
Requires-Dist: tenacity>=8.2.3
Requires-Dist: anyio
Requires-Dist: asyncer==0.0.8
Requires-Dist: cachetools>=5.5.0
Requires-Dist: cloudpickle>=3.0.0
Requires-Dist: rich>=13.7.1
Requires-Dist: numpy>=1.26.0
Requires-Dist: xxhash>=3.5.0
Provides-Extra: anthropic
Requires-Dist: anthropic<1.0.0,>=0.18.0; extra == "anthropic"
Provides-Extra: weaviate
Requires-Dist: weaviate-client~=4.5.4; extra == "weaviate"
Provides-Extra: mcp
Requires-Dist: mcp; python_version >= "3.10" and extra == "mcp"
Provides-Extra: langchain
Requires-Dist: langchain_core; extra == "langchain"
Provides-Extra: dev
Requires-Dist: pytest>=6.2.5; extra == "dev"
Requires-Dist: pytest-mock>=3.12.0; extra == "dev"
Requires-Dist: pytest-asyncio>=0.26.0; extra == "dev"
Requires-Dist: ruff>=0.3.0; extra == "dev"
Requires-Dist: pre-commit>=3.7.0; extra == "dev"
Requires-Dist: pillow>=10.1.0; extra == "dev"
Requires-Dist: datamodel_code_generator>=0.26.3; extra == "dev"
Requires-Dist: build>=1.0.3; extra == "dev"
Requires-Dist: litellm>=1.64.0; sys_platform == "win32" and extra == "dev"
Requires-Dist: litellm[proxy]>=1.64.0; sys_platform != "win32" and extra == "dev"
Provides-Extra: test-extras
Requires-Dist: mcp; python_version >= "3.10" and extra == "test-extras"
Requires-Dist: datasets>=2.14.6; extra == "test-extras"
Requires-Dist: pandas>=2.1.1; extra == "test-extras"
Requires-Dist: optuna>=3.4.0; extra == "test-extras"
Requires-Dist: langchain_core; extra == "test-extras"
Dynamic: license-file
